example
coyote_framework
