Metadata-Version: 1.1
Name: coyote-framework
Version: 0.1.1
Summary: Python-based testing framework
Home-page: https://github.com/Shapeways/coyote_framework
Author: Shapeways
Author-email: api@shapeways.com
License: UNKNOWN
Download-URL: https://github.com/Shapeways/coyote_framework/tarball/0.1.1
Platform: UNKNOWN
